pampu/__init__.py
pampu/__main__.py
pampu/cli.py
pampu/client.py
pampu-0.4.0.dist-info/licenses/LICENSE
pampu-0.4.0.dist-info/METADATA
pampu-0.4.0.dist-info/WHEEL
pampu-0.4.0.dist-info/entry_points.txt
pampu-0.4.0.dist-info/top_level.txt
pampu-0.4.0.dist-info/RECORD
