Metadata-Version: 2.4
Name: pampu
Version: 0.4.0
Summary: CLI for Atlassian Bamboo
License-Expression: MIT
Project-URL: Homepage, https://github.com/vivainio/pampu
Project-URL: Repository, https://github.com/vivainio/pampu
Project-URL: Issues, https://github.com/vivainio/pampu/issues
Keywords: bamboo,cli,atlassian,ci,cd
Classifier: Development Status :: 4 - Beta
Classifier: Environment :: Console
Classifier: Intended Audience :: Developers
Classifier: Operating System :: OS Independent
Classifier: Programming Language :: Python :: 3
Classifier: Programming Language :: Python :: 3.11
Classifier: Programming Language :: Python :: 3.12
Classifier: Programming Language :: Python :: 3.13
Classifier: Topic :: Software Development
Classifier: Topic :: Utilities
Requires-Python: >=3.11
License-File: LICENSE
Requires-Dist: atlassian-python-api>=3.41.0
Requires-Dist: platformdirs>=4.0.0
Dynamic: license-file
